NEMO_wago_interlocks/__init__.py
NEMO_wago_interlocks/apps.py
NEMO_wago_interlocks/interlocks.py
NEMO_wago_interlocks/migrations/0001_initial.py
NEMO_wago_interlocks/migrations/__init__.py
NEMO_wago_interlocks/tests/__init__.py
NEMO_wago_interlocks/tests/test_settings.py
nemo_wago_interlocks-1.0.0.dist-info/LICENSE
nemo_wago_interlocks-1.0.0.dist-info/METADATA
nemo_wago_interlocks-1.0.0.dist-info/WHEEL
nemo_wago_interlocks-1.0.0.dist-info/top_level.txt
nemo_wago_interlocks-1.0.0.dist-info/RECORD
