Metadata-Version: 2.2
Name: NEMO-wago-interlocks
Version: 1.0.0
Summary: WAGO Interlocks plugin for NEMO
Author-email: Atlantis Labs LLC <atlantis@atlantislabs.io>
License: MIT License
Project-URL: Homepage, https://gitlab.com/nemo-community/atlantis-labs/nemo-wago-interlocks
Project-URL: Changelog, https://gitlab.com/nemo-community/atlantis-labs/nemo-wago-interlocks/-/releases
Project-URL: Issues, https://gitlab.com/nemo-community/atlantis-labs/nemo-wago-interlocks/-/issues
Project-URL: CI, https://gitlab.com/nemo-community/atlantis-labs/nemo-wago-interlocks/-/pipelines
Keywords: NEMO
Classifier: Development Status :: 5 - Production/Stable
Classifier: Intended Audience :: Developers
Classifier: License :: OSI Approved :: MIT License
Classifier: Framework :: Django :: 4.2
Classifier: Programming Language :: Python :: 3.9
Classifier: Programming Language :: Python :: 3.10
Classifier: Programming Language :: Python :: 3.11
Classifier: Programming Language :: Python :: 3.12
Classifier: Programming Language :: Python :: 3.13
Requires-Python: >=3.8
License-File: LICENSE
Requires-Dist: django
Provides-Extra: nemo-ce
Requires-Dist: NEMO-CE>=1.7.0; extra == "nemo-ce"
Provides-Extra: nemo
Requires-Dist: NEMO>=4.7.0; extra == "nemo"
Provides-Extra: dev-tools
Requires-Dist: pre-commit; extra == "dev-tools"
Requires-Dist: djlint; extra == "dev-tools"
Requires-Dist: black; extra == "dev-tools"
